_readSTDF.cp36-win_amd64.pyd
readSTDF.py
readSTDF-0.0.1.dist-info/LICENSE
readSTDF-0.0.1.dist-info/METADATA
readSTDF-0.0.1.dist-info/WHEEL
readSTDF-0.0.1.dist-info/top_level.txt
readSTDF-0.0.1.dist-info/RECORD
